odoo/addons/sale_order_end_user/README.rst
odoo/addons/sale_order_end_user/__init__.py
odoo/addons/sale_order_end_user/__manifest__.py
odoo/addons/sale_order_end_user/i18n/sale_order_end_user.pot
odoo/addons/sale_order_end_user/models/__init__.py
odoo/addons/sale_order_end_user/models/sale_order.py
odoo/addons/sale_order_end_user/readme/CONTRIBUTORS.rst
odoo/addons/sale_order_end_user/readme/DESCRIPTION.rst
odoo/addons/sale_order_end_user/readme/USAGE.rst
odoo/addons/sale_order_end_user/static/description/icon.png
odoo/addons/sale_order_end_user/static/description/index.html
odoo/addons/sale_order_end_user/views/sale_order.xml
odoo_addon_sale_order_end_user-16.0.1.0.0.2.dist-info/METADATA
odoo_addon_sale_order_end_user-16.0.1.0.0.2.dist-info/WHEEL
odoo_addon_sale_order_end_user-16.0.1.0.0.2.dist-info/top_level.txt
odoo_addon_sale_order_end_user-16.0.1.0.0.2.dist-info/RECORD
