Metadata-Version: 2.1
Name: odoo-addon-sale_order_end_user
Version: 16.0.1.0.0.2
Summary: Allows to define the end user in sale orders if there is an intermediate between shipping and this end user
Home-page: https://github.com/OCA/sale-workflow
Author: ACSONE SA/NV,Odoo Community Association (OCA)
Author-email: support@odoo-community.org
License: AGPL-3
Classifier: Programming Language :: Python
Classifier: Framework :: Odoo
Classifier: Framework :: Odoo :: 16.0
Classifier: License :: OSI Approved :: GNU Affero General Public License v3
Classifier: Development Status :: 4 - Beta
Requires-Python: >=3.10
Requires-Dist: odoo-addon-partner-contact-type-end-user<16.1dev,>=16.0dev
Requires-Dist: odoo<16.1dev,>=16.0a
